fastclf/__init__.py
fastclf/__version__.py
fastclf/decomposition.py
fastclf/modelinfo.py
fastweb3-0.0.0.dev0.dist-info/LICENSE
fastweb3-0.0.0.dev0.dist-info/METADATA
fastweb3-0.0.0.dev0.dist-info/WHEEL
fastweb3-0.0.0.dev0.dist-info/top_level.txt
fastweb3-0.0.0.dev0.dist-info/RECORD
